{"ORPHApacket":[{"ORPHApacketID":"98464","date":"2019-12-06 09:35:14","version":"1.3.1 \/ 4.1.7 [2019-11-24] (orientdb version)","copyright":"Orphanet (c) 2019","ORPHA":"98464","Name":[{"lang":"en","label":"X-linked syndromic intellectual disability"}],"PURL":"http:\/\/www.orpha.net\/ORDO\/Orphanet_98464","DisorderType":[{"Name":[{"lang":"en","label":"Category"}],"PURL":"http:\/\/www.orpha.net\/ORDO\/Orphanet_557495"}],"SubClassOfList":[{"Disorder":[{"Name":[{"lang":"en","label":"Rare syndromic intellectual disability"}],"ORPHA":"102369","PURL":"http:\/\/www.orpha.net\/ORDO\/Orphanet_102369"},{"Name":[{"lang":"en","label":"Rare genetic syndromic intellectual disability"}],"ORPHA":"183763","PURL":"http:\/\/www.orpha.net\/ORDO\/Orphanet_183763"}]}]}]}