{"ORPHApacket":[{"ORPHApacketID":"163531","date":"2019-07-19 07:03:56","version":"1.2.11 \/ 4.1.6 [2018-04-12] (orientdb version)","copyright":"Orphanet (c) 2019","ORPHA":"163531","Name":[{"lang":"en","label":"Chronic cutaneous lupus erythematosus"}],"PURL":"http:\/\/www.orpha.net\/ORDO\/Orphanet_163531","DisorderType":[{"Name":[{"lang":"en","label":"Group of phenomes"}],"PURL":"http:\/\/www.orpha.net\/ORDO\/Orphanet_377794"}],"SubClassOfList":[{"Disorder":[{"Name":[{"lang":"en","label":"Rare cutaneous lupus erythematosus"}],"ORPHA":"535","PURL":"http:\/\/www.orpha.net\/ORDO\/Orphanet_535"}]}],"TextSection":[{"Name":[{"lang":"en","label":"Disease definition"}],"Contents":"A form of cutaneous lupus erythematosus (CLE) that includes five different forms: discoid lupus erythematosus (DLE), chilblain lupus, hypertrophic or verrucous lupus erythematosus, lupus erythematosus tumidus, and lupus erythematosus panniculitis."}],"AverageAgeOfOnsetList":[{"count":"4","AverageAgeOfOnset":[{"Name":[{"lang":"en","label":"Adolescent"}]},{"Name":[{"lang":"en","label":"Adult"}]},{"Name":[{"lang":"en","label":"Childhood"}]},{"Name":[{"lang":"en","label":"Elderly"}]}]}],"TypeOfInheritanceList":[{"count":"1","TypeOfInheritance":[{"Name":[{"lang":"en","label":"Multigenic\/multifactorial"}]}]}]}]}