{"ORPHApacket":[{"ORPHApacketID":"404584","date":"2019-12-06 04:41:38","version":"1.3.1 \/ 4.1.7 [2019-11-24] (orientdb version)","copyright":"Orphanet (c) 2019","ORPHA":"404584","Name":[{"lang":"en","label":"Rare genetic bone development disorder"}],"PURL":"http:\/\/www.orpha.net\/ORDO\/Orphanet_404584","DisorderType":[{"Name":[{"lang":"en","label":"Category"}],"PURL":"http:\/\/www.orpha.net\/ORDO\/Orphanet_557495"}],"SubClassOfList":[{"Disorder":[{"Name":[{"lang":"en","label":"Rare genetic developmental defect during embryogenesis"}],"ORPHA":"183530","PURL":"http:\/\/www.orpha.net\/ORDO\/Orphanet_183530"}]}],"SynonymList":[{"count":"1","Synonym":[{"lang":"en","label":"Rare genetic skeletal development disorder"}]}]}]}