{"ORPHApacket":[{"ORPHApacketID":"500533","date":"2019-12-06 06:05:00","version":"1.3.1 \/ 4.1.7 [2019-11-24] (orientdb version)","copyright":"Orphanet (c) 2019","ORPHA":"500533","Name":[{"lang":"en","label":"Polyhydramnios-megalencephaly-symptomatic epilepsy syndrome"}],"PURL":"http:\/\/www.orpha.net\/ORDO\/Orphanet_500533","DisorderType":[{"Name":[{"lang":"en","label":"Disease"}],"PURL":"http:\/\/www.orpha.net\/ORDO\/Orphanet_377788"}],"SubClassOfList":[{"Disorder":[{"Name":[{"lang":"en","label":"Rare syndromic intellectual disability"}],"ORPHA":"102369","PURL":"http:\/\/www.orpha.net\/ORDO\/Orphanet_102369"},{"Name":[{"lang":"en","label":"Monogenic disease with epilepsy"}],"ORPHA":"166472","PURL":"http:\/\/www.orpha.net\/ORDO\/Orphanet_166472"},{"Name":[{"lang":"en","label":"Rare genetic syndromic intellectual disability"}],"ORPHA":"183763","PURL":"http:\/\/www.orpha.net\/ORDO\/Orphanet_183763"}]}],"ExternalReferenceList":[{"count":"1","ExternalReference":[{"Source":"OMIM","Reference":"611087","DisorderMappingRelation":[{"id":"21527","Name":[{"lang":"en","label":"E (exact mapping (the terms and the concepts are equivalent))"}]}]}]}],"AverageAgeOfOnsetList":[{"count":"2","AverageAgeOfOnset":[{"Name":[{"lang":"en","label":"Infancy"}]},{"Name":[{"lang":"en","label":"Neonatal"}]}]}],"TypeOfInheritanceList":[{"count":"1","TypeOfInheritance":[{"Name":[{"lang":"en","label":"Autosomal recessive"}]}]}],"SynonymList":[{"count":"1","Synonym":[{"lang":"en","label":"PMSE syndrome"}]}],"DisorderGeneAssociationList":[{"count":"1","DisorderGeneAssociation":[{"Gene":[{"Name":[{"lang":"en","label":"STE20 related adaptor alpha"}],"Symbol":"STRADA","ExternalReferenceList":[{"count":"1","ExternalReference":[{"Source":"HGNC","Reference":"30172"}]}]}],"DisorderGeneAssociationType":[{"OrphaNumber":"410295","Name":[{"lang":"en","label":"Disease-causing germline mutation(s) (loss of function) in"}]}]}]}]}]}