{"ORPHApacket":[{"ORPHApacketID":"329255","date":"2019-12-06 03:42:33","version":"1.3.1 \/ 4.1.7 [2019-11-24] (orientdb version)","copyright":"Orphanet (c) 2019","ORPHA":"329255","Name":[{"lang":"en","label":"Blepharophimosis-intellectual disability syndrome due to UBE3B deficiency"}],"PURL":"http:\/\/www.orpha.net\/ORDO\/Orphanet_329255","DisorderType":[{"Name":[{"lang":"en","label":"Disease"}],"PURL":"http:\/\/www.orpha.net\/ORDO\/Orphanet_377788"}],"SubClassOfList":"","ExternalReferenceList":[{"count":"1","ExternalReference":[{"Source":"OMIM","Reference":"615057","DisorderMappingRelation":[{"id":"21527","Name":[{"lang":"en","label":"E (exact mapping (the terms and the concepts are equivalent))"}]}]}]}]}]}