{
    "Orphapacket": {
        "ORPHApacketId": "93448",
        "creationDate": "2024-07-01 09:48:26",
        "version": "1.3.29 / 4.1.7 [2023-08-02] (orientdb version)",
        "copyright": "Orphanet (c) 2024",
        "ORPHAcode": "93448",
        "Label": "Lysosomal storage disease with skeletal involvement",
        "PURL": "http://www.orpha.net/ORDO/Orphanet_93448",
        "DisorderType": {
            "value": "Category",
            "PURL": "http://www.orpha.net/ORDO/Orphanet_557495"
        },
        "Synonyms": [
            {
                "Synonym": "Dysostosis multiplex"
            }
        ],
        "Parents": [
            {
                "Parent": [
                    {
                        "ORPHAcode": "93419",
                        "Label": "Rare bone disease"
                    }
                ]
            },
            {
                "Parent": [
                    {
                        "ORPHAcode": "183524",
                        "Label": "Rare genetic bone disease"
                    }
                ]
            }
        ],
        "Childs": [
            {
                "Child": {
                    "Label": "Alpha-mannosidosis",
                    "ORPHAcode": "61",
                    "Genes": "no data"
                }
            },
            {
                "Child": {
                    "Label": "Aspartylglucosaminuria",
                    "ORPHAcode": "93",
                    "Genes": [
                        {
                            "Gene": {
                                "Label": "aspartylglucosaminidase",
                                "Symbol": "AGA",
                                "ExternalReferences": [
                                    {
                                        "Source": "HGNC",
                                        "Reference": "318"
                                    },
                                    {
                                        "Source": "OMIM",
                                        "Reference": "613228"
                                    }
                                ],
                                "DisorderGeneAssociationType": "Disease-causing germline mutation(s) in"
                            }
                        }
                    ]
                }
            },
            {
                "Child": {
                    "Label": "Multiple sulfatase deficiency",
                    "ORPHAcode": "585",
                    "Genes": [
                        {
                            "Gene": {
                                "Label": "sulfatase modifying factor 1",
                                "Symbol": "SUMF1",
                                "ExternalReferences": [
                                    {
                                        "Source": "HGNC",
                                        "Reference": "20376"
                                    },
                                    {
                                        "Source": "OMIM",
                                        "Reference": "607939"
                                    }
                                ],
                                "DisorderGeneAssociationType": "Disease-causing germline mutation(s) in"
                            }
                        }
                    ]
                }
            },
            {
                "Child": {
                    "Label": "Beta-mannosidosis",
                    "ORPHAcode": "118",
                    "Genes": [
                        {
                            "Gene": {
                                "Label": "mannosidase beta",
                                "Symbol": "MANBA",
                                "ExternalReferences": [
                                    {
                                        "Source": "HGNC",
                                        "Reference": "6831"
                                    },
                                    {
                                        "Source": "OMIM",
                                        "Reference": "609489"
                                    }
                                ],
                                "DisorderGeneAssociationType": "Disease-causing germline mutation(s) in"
                            }
                        }
                    ]
                }
            },
            {
                "Child": {
                    "Label": "Fucosidosis",
                    "ORPHAcode": "349",
                    "Genes": [
                        {
                            "Gene": {
                                "Label": "alpha-L-fucosidase 1",
                                "Symbol": "FUCA1",
                                "ExternalReferences": [
                                    {
                                        "Source": "HGNC",
                                        "Reference": "4006"
                                    },
                                    {
                                        "Source": "OMIM",
                                        "Reference": "612280"
                                    }
                                ],
                                "DisorderGeneAssociationType": "Disease-causing germline mutation(s) in"
                            }
                        }
                    ]
                }
            },
            {
                "Child": {
                    "Label": "Mucopolysaccharidosis type 6",
                    "ORPHAcode": "583",
                    "Genes": "no data"
                }
            },
            {
                "Child": {
                    "Label": "Mucolipidosis type II",
                    "ORPHAcode": "576",
                    "Genes": [
                        {
                            "Gene": {
                                "Label": "N-acetylglucosamine-1-phosphate transferase subunits alpha and beta",
                                "Symbol": "GNPTAB",
                                "ExternalReferences": [
                                    {
                                        "Source": "HGNC",
                                        "Reference": "29670"
                                    },
                                    {
                                        "Source": "OMIM",
                                        "Reference": "607840"
                                    }
                                ],
                                "DisorderGeneAssociationType": "Disease-causing germline mutation(s) (loss of function) in"
                            }
                        }
                    ]
                }
            },
            {
                "Child": {
                    "Label": "Mucolipidosis type III",
                    "ORPHAcode": "577",
                    "Genes": "no data"
                }
            },
            {
                "Child": {
                    "Label": "Mucopolysaccharidosis type 7",
                    "ORPHAcode": "584",
                    "Genes": [
                        {
                            "Gene": {
                                "Label": "glucuronidase beta",
                                "Symbol": "GUSB",
                                "ExternalReferences": [
                                    {
                                        "Source": "HGNC",
                                        "Reference": "4696"
                                    },
                                    {
                                        "Source": "OMIM",
                                        "Reference": "611499"
                                    }
                                ],
                                "DisorderGeneAssociationType": "Disease-causing germline mutation(s) in"
                            }
                        }
                    ]
                }
            },
            {
                "Child": {
                    "Label": "Mucopolysaccharidosis type 2",
                    "ORPHAcode": "580",
                    "Genes": "no data"
                }
            },
            {
                "Child": {
                    "Label": "Mucopolysaccharidosis type 1",
                    "ORPHAcode": "579",
                    "Genes": "no data"
                }
            },
            {
                "Child": {
                    "Label": "Galactosialidosis",
                    "ORPHAcode": "351",
                    "Genes": [
                        {
                            "Gene": {
                                "Label": "cathepsin A",
                                "Symbol": "CTSA",
                                "ExternalReferences": [
                                    {
                                        "Source": "HGNC",
                                        "Reference": "9251"
                                    },
                                    {
                                        "Source": "OMIM",
                                        "Reference": "613111"
                                    }
                                ],
                                "DisorderGeneAssociationType": "Disease-causing germline mutation(s) in"
                            }
                        }
                    ]
                }
            },
            {
                "Child": {
                    "Label": "Free sialic acid storage disease, infantile form",
                    "ORPHAcode": "309324",
                    "Genes": [
                        {
                            "Gene": {
                                "Label": "solute carrier family 17 member 5",
                                "Symbol": "SLC17A5",
                                "ExternalReferences": [
                                    {
                                        "Source": "HGNC",
                                        "Reference": "10933"
                                    },
                                    {
                                        "Source": "OMIM",
                                        "Reference": "604322"
                                    }
                                ],
                                "DisorderGeneAssociationType": "Disease-causing germline mutation(s) in"
                            }
                        }
                    ]
                }
            },
            {
                "Child": {
                    "Label": "GM1 gangliosidosis",
                    "ORPHAcode": "354",
                    "Genes": "no data"
                }
            },
            {
                "Child": {
                    "Label": "Mucopolysaccharidosis type 3",
                    "ORPHAcode": "581",
                    "Genes": "no data"
                }
            },
            {
                "Child": {
                    "Label": "Mucopolysaccharidosis type 4",
                    "ORPHAcode": "582",
                    "Genes": "no data"
                }
            },
            {
                "Child": {
                    "Label": "Hyaluronidase deficiency",
                    "ORPHAcode": "67041",
                    "Genes": [
                        {
                            "Gene": {
                                "Label": "hyaluronidase 1",
                                "Symbol": "HYAL1",
                                "ExternalReferences": [
                                    {
                                        "Source": "HGNC",
                                        "Reference": "5320"
                                    },
                                    {
                                        "Source": "OMIM",
                                        "Reference": "607071"
                                    }
                                ],
                                "DisorderGeneAssociationType": "Disease-causing germline mutation(s) in"
                            }
                        }
                    ]
                }
            },
            {
                "Child": {
                    "Label": "Sialidosis type 2",
                    "ORPHAcode": "87876",
                    "Genes": "no data"
                }
            },
            {
                "Child": {
                    "Label": "Mucopolysaccharidosis type 10",
                    "ORPHAcode": "662216",
                    "Genes": [
                        {
                            "Gene": {
                                "Label": "arylsulfatase family member K",
                                "Symbol": "ARSK",
                                "ExternalReferences": [
                                    {
                                        "Source": "OMIM",
                                        "Reference": "610011"
                                    },
                                    {
                                        "Source": "HGNC",
                                        "Reference": "25239"
                                    }
                                ],
                                "DisorderGeneAssociationType": "Disease-causing germline mutation(s) in"
                            }
                        }
                    ]
                }
            }
        ]
    }
}