{
    "Orphapacket": {
        "ORPHApacketId": "67039",
        "creationDate": "2025-12-08 06:52:43",
        "version": "1.3.42 / 4.1.8 [2025-03-03]",
        "copyright": "Orphanet (c) 2025",
        "ORPHAcode": "67039",
        "Label": "Segmental odontomaxillary dysplasia",
        "PURL": "http://www.orpha.net/ORDO/Orphanet_67039",
        "DisorderType": {
            "value": "Disease",
            "PURL": "http://www.orpha.net/ORDO/Orphanet_377788"
        },
        "TextSection": {
            "TextSectionType": "Definition",
            "Contents": "A rare oral disease characterized by unilateral enlargement of the right or left maxillary alveolar bone and gingiva in the region distal to the canines towards the maxillary tuberosity. In the enlarged region dental abnormalities such as missing teeth abnormal spacing and delayed eruption occur."
        },
        "Parents": [
            {
                "Parent": [
                    {
                        "ORPHAcode": "164001",
                        "Label": "Rare odontal or periodontal disorder"
                    }
                ]
            }
        ],
        "Prevalences": [
            {
                "Prevalence": {
                    "Source": "ORPHANET",
                    "PrevalenceType": "Cases/families",
                    "PrevalenceQualification": "Case(s)",
                    "PrevalenceClass": "no data",
                    "ValMoy": "no data",
                    "PrevalenceGeographic": "Worldwide"
                }
            },
            {
                "Prevalence": {
                    "Source": "ORPHANET",
                    "PrevalenceType": "Point prevalence",
                    "PrevalenceQualification": "Class only",
                    "PrevalenceClass": "<1 / 1 000 000",
                    "ValMoy": "no data",
                    "PrevalenceGeographic": "Worldwide"
                }
            }
        ],
        "AverageAgeOfOnsets": {
            "AverageAgeOfOnset": [
                {
                    "value": "Childhood"
                }
            ]
        },
        "TypeOfInheritances": {
            "TypeOfInheritance": [
                {
                    "value": "Not applicable"
                }
            ]
        }
    }
}