{
    "Orphapacket": {
        "ORPHApacketId": "589527",
        "creationDate": "2020-12-03 15:53:15",
        "version": "1.3.6 / 4.1.7 [2020-04-17] (orientdb version)",
        "copyright": "Orphanet (c) 2020",
        "ORPHAcode": "589527",
        "Label": "Spinocerebellar ataxia type 45",
        "PURL": "http://www.orpha.net/ORDO/Orphanet_589527",
        "DisorderType": {
            "value": "Disease",
            "PURL": "http://www.orpha.net/ORDO/Orphanet_377788"
        },
        "Synonyms": [
            {
                "Synonym": "SCA45"
            }
        ],
        "Parents": [
            {
                "Parent": [
                    {
                        "ORPHAcode": "94148",
                        "Label": "Autosomal dominant cerebellar ataxia type III"
                    }
                ]
            }
        ]
    }
}