{
    "Orphapacket": {
        "ORPHApacketId": "93928",
        "creationDate": "2024-12-03 10:13:55",
        "version": "1.3.29 / 4.1.7 [2023-08-02] (orientdb version)",
        "copyright": "Orphanet (c) 2024",
        "ORPHAcode": "93928",
        "Label": "Isolated epispadias",
        "PURL": "http://www.orpha.net/ORDO/Orphanet_93928",
        "DisorderType": {
            "value": "Clinical subtype",
            "PURL": "http://www.orpha.net/ORDO/Orphanet_377796"
        },
        "TextSection": {
            "TextSectionType": "Definition",
            "Contents": "A congenital genitourinary malformation belonging to the spectrum of the exstrophy-epispadias complex (EEC) and is characterized in males by an ectopic meatus or a mucosal strip in place of the urethra on the penile dorsum and in females by bifid clitoris and a variable cleft of the urethra."
        },
        "Parents": [
            {
                "Parent": [
                    {
                        "ORPHAcode": "322",
                        "Label": "Exstrophy-epispadias complex"
                    }
                ]
            }
        ],
        "Phenotypes": [
            {
                "Phenotype": {
                    "HPOId": "HP:0030911",
                    "HPOTerm": "Bifid clitoris",
                    "HPOFrequency": "Occasional (29-5%)"
                }
            },
            {
                "Phenotype": {
                    "HPOId": "HP:0000039",
                    "HPOTerm": "Epispadias",
                    "HPOFrequency": "Very frequent (99-80%)"
                }
            },
            {
                "Phenotype": {
                    "HPOId": "HP:0008648",
                    "HPOTerm": "Anteriorly displaced urethral meatus",
                    "HPOFrequency": "Very frequent (99-80%)"
                }
            },
            {
                "Phenotype": {
                    "HPOId": "HP:0000020",
                    "HPOTerm": "Urinary incontinence",
                    "HPOFrequency": "Frequent (79-30%)"
                }
            },
            {
                "Phenotype": {
                    "HPOId": "HP:0000076",
                    "HPOTerm": "Vesicoureteral reflux",
                    "HPOFrequency": "Frequent (79-30%)"
                }
            },
            {
                "Phenotype": {
                    "HPOId": "HP:0002644",
                    "HPOTerm": "Abnormality of pelvic girdle bone morphology",
                    "HPOFrequency": "Frequent (79-30%)"
                }
            }
        ],
        "Prevalences": [
            {
                "Prevalence": {
                    "Source": "19878548[PMID]",
                    "PrevalenceType": "Prevalence at birth",
                    "PrevalenceQualification": "Value and class",
                    "PrevalenceClass": "1-9 / 100 000",
                    "ValMoy": "no data",
                    "PrevalenceGeographic": "Europe"
                }
            },
            {
                "Prevalence": {
                    "Source": "19878548[PMID]",
                    "PrevalenceType": "Point prevalence",
                    "PrevalenceQualification": "Class only",
                    "PrevalenceClass": "1-9 / 100 000",
                    "ValMoy": "no data",
                    "PrevalenceGeographic": "Europe"
                }
            }
        ],
        "AverageAgeOfOnsets": [
            {
                "AverageAgeOfOnset": {
                    "value": "Antenatal"
                }
            },
            {
                "AverageAgeOfOnset": {
                    "value": "Infancy"
                }
            },
            {
                "AverageAgeOfOnset": {
                    "value": "Neonatal"
                }
            }
        ],
        "TypeOfInheritances": {
            "TypeOfInheritance": [
                {
                    "value": "Multigenic/multifactorial"
                }
            ]
        }
    }
}