{
    "Orphapacket": {
        "ORPHApacketId": "519302",
        "creationDate": "2024-12-03 10:13:55",
        "version": "1.3.29 / 4.1.7 [2023-08-02] (orientdb version)",
        "copyright": "Orphanet (c) 2024",
        "ORPHAcode": "519302",
        "Label": "Isolated macular dystrophy",
        "PURL": "http://www.orpha.net/ORDO/Orphanet_519302",
        "DisorderType": {
            "value": "Category",
            "PURL": "http://www.orpha.net/ORDO/Orphanet_557495"
        },
        "Parents": [
            {
                "Parent": [
                    {
                        "ORPHAcode": "519306",
                        "Label": "Isolated progressive inherited retinal disorder"
                    }
                ]
            }
        ],
        "Childs": [
            {
                "Child": {
                    "Label": "Best vitelliform macular dystrophy",
                    "ORPHAcode": "1243",
                    "Genes": [
                        {
                            "Gene": {
                                "Label": "bestrophin 1",
                                "Symbol": "BEST1",
                                "ExternalReferences": [
                                    {
                                        "Source": "HGNC",
                                        "Reference": "12703"
                                    },
                                    {
                                        "Source": "OMIM",
                                        "Reference": "607854"
                                    }
                                ],
                                "DisorderGeneAssociationType": "Disease-causing germline mutation(s) in"
                            }
                        }
                    ]
                }
            },
            {
                "Child": {
                    "Label": "Stargardt disease",
                    "ORPHAcode": "827",
                    "Genes": [
                        {
                            "Gene": {
                                "Label": "ATP binding cassette subfamily A member 4",
                                "Symbol": "ABCA4",
                                "ExternalReferences": [
                                    {
                                        "Source": "HGNC",
                                        "Reference": "34"
                                    },
                                    {
                                        "Source": "OMIM",
                                        "Reference": "601691"
                                    }
                                ],
                                "DisorderGeneAssociationType": "Disease-causing germline mutation(s) in"
                            }
                        },
                        {
                            "Gene": {
                                "Label": "ELOVL fatty acid elongase 4",
                                "Symbol": "ELOVL4",
                                "ExternalReferences": [
                                    {
                                        "Source": "HGNC",
                                        "Reference": "14415"
                                    },
                                    {
                                        "Source": "OMIM",
                                        "Reference": "605512"
                                    }
                                ],
                                "DisorderGeneAssociationType": "Disease-causing germline mutation(s) in"
                            }
                        },
                        {
                            "Gene": {
                                "Label": "prominin 1",
                                "Symbol": "PROM1",
                                "ExternalReferences": [
                                    {
                                        "Source": "HGNC",
                                        "Reference": "9454"
                                    },
                                    {
                                        "Source": "OMIM",
                                        "Reference": "604365"
                                    }
                                ],
                                "DisorderGeneAssociationType": "Disease-causing germline mutation(s) in"
                            }
                        }
                    ]
                }
            },
            {
                "Child": {
                    "Label": "Sorsby pseudoinflammatory fundus dystrophy",
                    "ORPHAcode": "59181",
                    "Genes": [
                        {
                            "Gene": {
                                "Label": "TIMP metallopeptidase inhibitor 3",
                                "Symbol": "TIMP3",
                                "ExternalReferences": [
                                    {
                                        "Source": "HGNC",
                                        "Reference": "11822"
                                    },
                                    {
                                        "Source": "OMIM",
                                        "Reference": "188826"
                                    }
                                ],
                                "DisorderGeneAssociationType": "Disease-causing germline mutation(s) in"
                            }
                        }
                    ]
                }
            },
            {
                "Child": {
                    "Label": "Pattern dystrophy",
                    "ORPHAcode": "63454",
                    "Genes": "no data"
                }
            },
            {
                "Child": {
                    "Label": "North Carolina macular dystrophy",
                    "ORPHAcode": "75327",
                    "Genes": [
                        {
                            "Gene": {
                                "Label": "DNase1 hypersensitivity, chromosome 6, site 1",
                                "Symbol": "DHS6S1",
                                "ExternalReferences": [
                                    {
                                        "ExternalReference": {
                                            "Source": "OMIM",
                                            "Reference": "616842"
                                        }
                                    }
                                ],
                                "DisorderGeneAssociationType": "Disease-causing germline mutation(s) in"
                            }
                        }
                    ]
                }
            },
            {
                "Child": {
                    "Label": "Central areolar choroidal dystrophy",
                    "ORPHAcode": "75377",
                    "Genes": [
                        {
                            "Gene": {
                                "Label": "guanylate cyclase activator 1A",
                                "Symbol": "GUCA1A",
                                "ExternalReferences": [
                                    {
                                        "Source": "HGNC",
                                        "Reference": "4678"
                                    },
                                    {
                                        "Source": "OMIM",
                                        "Reference": "600364"
                                    }
                                ],
                                "DisorderGeneAssociationType": "Disease-causing germline mutation(s) (gain of function) in"
                            }
                        },
                        {
                            "Gene": {
                                "Label": "peripherin 2",
                                "Symbol": "PRPH2",
                                "ExternalReferences": [
                                    {
                                        "Source": "HGNC",
                                        "Reference": "9942"
                                    },
                                    {
                                        "Source": "OMIM",
                                        "Reference": "179605"
                                    }
                                ],
                                "DisorderGeneAssociationType": "Disease-causing germline mutation(s) in"
                            }
                        },
                        {
                            "Gene": {
                                "Label": "guanylate cyclase 2D, retinal",
                                "Symbol": "GUCY2D",
                                "ExternalReferences": [
                                    {
                                        "Source": "HGNC",
                                        "Reference": "4689"
                                    },
                                    {
                                        "Source": "OMIM",
                                        "Reference": "600179"
                                    }
                                ],
                                "DisorderGeneAssociationType": "Disease-causing germline mutation(s) in"
                            }
                        }
                    ]
                }
            },
            {
                "Child": {
                    "Label": "Cystoid macular dystrophy",
                    "ORPHAcode": "75381",
                    "Genes": "no data"
                }
            },
            {
                "Child": {
                    "Label": "Occult macular dystrophy",
                    "ORPHAcode": "247834",
                    "Genes": [
                        {
                            "Gene": {
                                "Label": "RP1 like 1",
                                "Symbol": "RP1L1",
                                "ExternalReferences": [
                                    {
                                        "Source": "HGNC",
                                        "Reference": "15946"
                                    },
                                    {
                                        "Source": "OMIM",
                                        "Reference": "608581"
                                    }
                                ],
                                "DisorderGeneAssociationType": "Disease-causing germline mutation(s) in"
                            }
                        }
                    ]
                }
            },
            {
                "Child": {
                    "Label": "Benign concentric annular macular dystrophy",
                    "ORPHAcode": "251287",
                    "Genes": [
                        {
                            "Gene": {
                                "Label": "interphotoreceptor matrix proteoglycan 1",
                                "Symbol": "IMPG1",
                                "ExternalReferences": [
                                    {
                                        "Source": "HGNC",
                                        "Reference": "6055"
                                    },
                                    {
                                        "Source": "OMIM",
                                        "Reference": "602870"
                                    }
                                ],
                                "DisorderGeneAssociationType": "Disease-causing germline mutation(s) in"
                            }
                        }
                    ]
                }
            },
            {
                "Child": {
                    "Label": "Retinal macular dystrophy type 2",
                    "ORPHAcode": "319640",
                    "Genes": [
                        {
                            "Gene": {
                                "Label": "prominin 1",
                                "Symbol": "PROM1",
                                "ExternalReferences": [
                                    {
                                        "Source": "HGNC",
                                        "Reference": "9454"
                                    },
                                    {
                                        "Source": "OMIM",
                                        "Reference": "604365"
                                    }
                                ],
                                "DisorderGeneAssociationType": "Disease-causing germline mutation(s) in"
                            }
                        }
                    ]
                }
            }
        ]
    }
}